[
	{
		"Institucion": "Aalto University"
	},
	{
		"Institucion": "Academia de Historia de Occidente"
	},
	{
		"Institucion": "Aix-Marseille Université"
	},
	{
		"Institucion": "Arizona University"
	},
	{
		"Institucion": "Asesor Científico"
	},
	{
		"Institucion": "Asociación Civil"
	},
	{
		"Institucion": "Bellas Artes "
	},
	{
		"Institucion": "Benemérita Universidad Autónoma de Puebla"
	},
	{
		"Institucion": "Benemérita y Centenaria Escuela Normal de Jalisco"
	},
	{
		"Institucion": "Bosque Trópical AC"
	},
	{
		"Institucion": "CETIS"
	},
	{
		"Institucion": "CFE"
	},
	{
		"Institucion": "CIATDEJ"
	},
	{
		"Institucion": "CIATEJ"
	},
	{
		"Institucion": "CICESE"
	},
	{
		"Institucion": "CIDE"
	},
	{
		"Institucion": "CIESAS"
	},
	{
		"Institucion": "CIESAS-Occidente"
	},
	{
		"Institucion": "CIESAS-Peninsular"
	},
	{
		"Institucion": "CIFAP-Jalisco"
	},
	{
		"Institucion": "CINVESTAV"
	},
	{
		"Institucion": "CONACYT"
	},
	{
		"Institucion": "CRILAR"
	},
	{
		"Institucion": "CSIC"
	},
	{
		"Institucion": "California Academy of Sciences"
	},
	{
		"Institucion": "California Institute of Technology"
	},
	{
		"Institucion": "Casa Herradura"
	},
	{
		"Institucion": "Center for Latin American Monetary Studies"
	},
	{
		"Institucion": "Centre de Recherche er de Restauration des Musée de France"
	},
	{
		"Institucion": "Centro Regional del Bajío"
	},
	{
		"Institucion": "Centro de Estudios Mexicanos y Centroamericanos"
	},
	{
		"Institucion": "Centro de Investigaciones Científicas de Yucatán"
	},
	{
		"Institucion": "Centro de Investigaciones y Estudios Superiores en Antropología Social"
	},
	{
		"Institucion": "Centro de Investigación Científica de Yucatán"
	},
	{
		"Institucion": "Centro de Investigación Científica y de Educación Superior de Ensenada"
	},
	{
		"Institucion": "Centro de Investigación en Alimentación y Desarrollo A.C."
	},
	{
		"Institucion": "Centro de Investigación en Matemáticas"
	},
	{
		"Institucion": "Centro de Investigación y Asistencia en Tecnología y Diseño del Estado…"
	},
	{
		"Institucion": "Centro de Investigación y Educación Superior de Ensenada"
	},
	{
		"Institucion": "Centro de Investigacón matemáticas"
	},
	{
		"Institucion": "Centro de Política del Suelo y Valoraciones"
	},
	{
		"Institucion": "Centro de estudios Superiores del Golfo"
	},
	{
		"Institucion": "Colegio San Ildefonso"
	},
	{
		"Institucion": "Colegio de Arquitectos de Ciudad Juárez"
	},
	{
		"Institucion": "Colegio de Arquitectos de Nuevo León"
	},
	{
		"Institucion": "Colegio de Postgraduados"
	},
	{
		"Institucion": "Colegio de Postgraduados - Campus Montecillos"
	},
	{
		"Institucion": "Colegio de Postgraduados - Campus Veracruz"
	},
	{
		"Institucion": "Colegio de Postgraduados en Ciencias Agrícolas - Campus Puebla"
	},
	{
		"Institucion": "Colorado State University"
	},
	{
		"Institucion": "Consejo Estatal Contra las Adicciones"
	},
	{
		"Institucion": "Consejo Regulador del Tequila"
	},
	{
		"Institucion": "Cornell University"
	},
	{
		"Institucion": "Corporación Universitaria Iberoamericana"
	},
	{
		"Institucion": "Darwinweg"
	},
	{
		"Institucion": "Delft University of Technology"
	},
	{
		"Institucion": "Desert Botanical Garden"
	},
	{
		"Institucion": "Dirección General de Educación Normal y Actualización del Magisterio"
	},
	{
		"Institucion": "Drew University"
	},
	{
		"Institucion": "East Carolina University"
	},
	{
		"Institucion": "Ecole Nationale Supérieure des Ingénieurs en Arts Chimiques et Technol…"
	},
	{
		"Institucion": "El Colegio Mexiquense"
	},
	{
		"Institucion": "El Colegio de Jalisco"
	},
	{
		"Institucion": "El Colegio de Michoacán"
	},
	{
		"Institucion": "El Colegio de México"
	},
	{
		"Institucion": "El Colegio de la Frontera Norte"
	},
	{
		"Institucion": "El Colegio de la Frontera Sur"
	},
	{
		"Institucion": "Escuela Nacional de Antropología E Historia"
	},
	{
		"Institucion": "Escuela Nacional de Ciencias Biológicas"
	},
	{
		"Institucion": "Escuela Normal Experimental de San Antonio Matute"
	},
	{
		"Institucion": "Escuela Normal Superior Nueva Galicia"
	},
	{
		"Institucion": "Escuela de Conservación y Restauración de Occidente"
	},
	{
		"Institucion": "Geochronology Center"
	},
	{
		"Institucion": "Gobierno Municipal de Guachinango"
	},
	{
		"Institucion": "Gobierno del Estado de Jalisco"
	},
	{
		"Institucion": "ICOMOS"
	},
	{
		"Institucion": "IMSS"
	},
	{
		"Institucion": "INAH"
	},
	{
		"Institucion": "INEGI"
	},
	{
		"Institucion": "INIFAP"
	},
	{
		"Institucion": "IPICYT"
	},
	{
		"Institucion": "IPN"
	},
	{
		"Institucion": "ITESO"
	},
	{
		"Institucion": "Indiana University Bloomington"
	},
	{
		"Institucion": "Iniciativa Privada"
	},
	{
		"Institucion": "Institut de Recherche pour le Développement"
	},
	{
		"Institucion": "Instituto Francés de Investigación Científica y Técnica para el Desarr…"
	},
	{
		"Institucion": "Instituto Mora"
	},
	{
		"Institucion": "Instituto Nacional de Antropología e Historia"
	},
	{
		"Institucion": "Instituto Potosino de Investigación Científica y Tecnológica"
	},
	{
		"Institucion": "Instituto Superior de Investigación y Docencia para el Magisterio"
	},
	{
		"Institucion": "Instituto Tecnologico Mario Molina"
	},
	{
		"Institucion": "Instituto Tecnológico Autónomo de México"
	},
	{
		"Institucion": "Instituto Tecnológico José Mario Molina Pasquel y Henríquez"
	},
	{
		"Institucion": "Instituto Tecnológico Superior de Tacámbaro"
	},
	{
		"Institucion": "Instituto Tecnológico Superior de Zongolica"
	},
	{
		"Institucion": "Instituto Tecnológico de Ciudad Victoria"
	},
	{
		"Institucion": "Instituto Tecnológico de Tlajomulco"
	},
	{
		"Institucion": "Instituto de Ciencia Animal"
	},
	{
		"Institucion": "Instituto de Ecología A.C."
	},
	{
		"Institucion": "Instituto de Investigaciones Nucleares"
	},
	{
		"Institucion": "KTH Royal Institute of Technology"
	},
	{
		"Institucion": "Laurentian Forestry Centre"
	},
	{
		"Institucion": "Louisiana State University"
	},
	{
		"Institucion": "MIT"
	},
	{
		"Institucion": "Mercy Corps"
	},
	{
		"Institucion": "Missouri Botanical Garden"
	},
	{
		"Institucion": "Missouri University"
	},
	{
		"Institucion": "Museo Nacional de Ciencias Naturales (España)"
	},
	{
		"Institucion": "Museum of Nothern Arizona"
	},
	{
		"Institucion": "Muséum national d'histoire naturelle en París"
	},
	{
		"Institucion": "NASA"
	},
	{
		"Institucion": "NHK"
	},
	{
		"Institucion": "National Center for Toxicological Research"
	},
	{
		"Institucion": "National Centre for Disease Control and Prevention Programs"
	},
	{
		"Institucion": "National Research Institute of Fisheries"
	},
	{
		"Institucion": "New York University"
	},
	{
		"Institucion": "North Carolina State Museum of Natural Sciencies"
	},
	{
		"Institucion": "North Carolina State University"
	},
	{
		"Institucion": "Occidental Collage"
	},
	{
		"Institucion": "Ohio State University"
	},
	{
		"Institucion": "Pontificia Universidad Javeriana"
	},
	{
		"Institucion": "Purdue University"
	},
	{
		"Institucion": "Researche Centre for Geospatial Information Sciences"
	},
	{
		"Institucion": "Rocky Mountain Research Station"
	},
	{
		"Institucion": "S/I"
	},
	{
		"Institucion": "San Antonio Health Center"
	},
	{
		"Institucion": "Secretaría de Educación Jalisco"
	},
	{
		"Institucion": "Secretaría de Educación Pública"
	},
	{
		"Institucion": "Secretaría de Salud Jalisco"
	},
	{
		"Institucion": "Secretaría de Salud y Bienestar Social del Estado de Jalisco"
	},
	{
		"Institucion": "Sector Gubernamental"
	},
	{
		"Institucion": "Smithsonian Institute"
	},
	{
		"Institucion": "Smithsonian Tropical Research Institute"
	},
	{
		"Institucion": "Southeastern Louisiana University"
	},
	{
		"Institucion": "Stanford University"
	},
	{
		"Institucion": "TEC de Monterrey"
	},
	{
		"Institucion": "Teagasc Environmental Research Centre"
	},
	{
		"Institucion": "Tecnológico Nacional de México"
	},
	{
		"Institucion": "Texas A&M University"
	},
	{
		"Institucion": "Texas Wesleyan University"
	},
	{
		"Institucion": "The University of Michigan"
	},
	{
		"Institucion": "The University of New Mexico"
	},
	{
		"Institucion": "Tohoku University"
	},
	{
		"Institucion": "UC Irvine"
	},
	{
		"Institucion": "UFPel"
	},
	{
		"Institucion": "UMR"
	},
	{
		"Institucion": "UNESCO-IHE Institute for Water Education"
	},
	{
		"Institucion": "US Departament of Agriculture"
	},
	{
		"Institucion": "USDA-ARS"
	},
	{
		"Institucion": "Univeridad Autonóma de Nuevo León"
	},
	{
		"Institucion": "Universidad Anáhuac México Norte"
	},
	{
		"Institucion": "Universidad Autonóma Benito Juárez "
	},
	{
		"Institucion": "Universidad Autínoma de Tlaxcala"
	},
	{
		"Institucion": "Universidad Autónoma Agraria Antonio Narro"
	},
	{
		"Institucion": "Universidad Autónoma Chapingo"
	},
	{
		"Institucion": "Universidad Autónoma Metropolitana"
	},
	{
		"Institucion": "Universidad Autónoma Metropolitana - Azcapotzalco"
	},
	{
		"Institucion": "Universidad Autónoma Metropolitana - Xochimilco"
	},
	{
		"Institucion": "Universidad Autónoma Metropolitana- Iztapalapa"
	},
	{
		"Institucion": "Universidad Autónoma de Aguascalientes"
	},
	{
		"Institucion": "Universidad Autónoma de Baja California"
	},
	{
		"Institucion": "Universidad Autónoma de Chapingo"
	},
	{
		"Institucion": "Universidad Autónoma de Chihuahua"
	},
	{
		"Institucion": "Universidad Autónoma de Guadalajara"
	},
	{
		"Institucion": "Universidad Autónoma de Guerrero"
	},
	{
		"Institucion": "Universidad Autónoma de Hidalgo"
	},
	{
		"Institucion": "Universidad Autónoma de Madrid"
	},
	{
		"Institucion": "Universidad Autónoma de Nayarit"
	},
	{
		"Institucion": "Universidad Autónoma de Nuevo León"
	},
	{
		"Institucion": "Universidad Autónoma de Querétaro"
	},
	{
		"Institucion": "Universidad Autónoma de San Luis Potosí"
	},
	{
		"Institucion": "Universidad Autónoma de Sinaloa"
	},
	{
		"Institucion": "Universidad Autónoma de Tamaulipas"
	},
	{
		"Institucion": "Universidad Autónoma de Zacatecas"
	},
	{
		"Institucion": "Universidad Autónoma del Estado de Hidalgo"
	},
	{
		"Institucion": "Universidad Autónoma del Estado de Morelos"
	},
	{
		"Institucion": "Universidad Autónoma del Estado de México"
	},
	{
		"Institucion": "Universidad Auónoma del Estado de México"
	},
	{
		"Institucion": "Universidad Carolina de Praga"
	},
	{
		"Institucion": "Universidad Complutense de Madrid"
	},
	{
		"Institucion": "Universidad Estatal de Arizona"
	},
	{
		"Institucion": "Universidad Estatal de California"
	},
	{
		"Institucion": "Universidad Estatal de Carolina del Norte"
	},
	{
		"Institucion": "Universidad Iberoamericana"
	},
	{
		"Institucion": "Universidad Jesuita de Guadalajara"
	},
	{
		"Institucion": "Universidad Juárez Autónoma de Tabasco"
	},
	{
		"Institucion": "Universidad Juárez del Estado de Durango"
	},
	{
		"Institucion": "Universidad La Salle"
	},
	{
		"Institucion": "Universidad Marista de Guadalajara"
	},
	{
		"Institucion": "Universidad Michoacana de San Nicolás de Hidalgo"
	},
	{
		"Institucion": "Universidad Nacional Autónoma de México"
	},
	{
		"Institucion": "Universidad Nacional de La Plata"
	},
	{
		"Institucion": "Universidad Nacional del Litoral"
	},
	{
		"Institucion": "Universidad Oberta de Cataluña"
	},
	{
		"Institucion": "Universidad Panamericana"
	},
	{
		"Institucion": "Universidad Pedagógica Nacional"
	},
	{
		"Institucion": "Universidad Rovira i Virgili"
	},
	{
		"Institucion": "Universidad Tecnológica de Chalmers"
	},
	{
		"Institucion": "Universidad Tecnológica de Jalisco"
	},
	{
		"Institucion": "Universidad Tecnológica de México"
	},
	{
		"Institucion": "Universidad Tecnológica de la Mixteca"
	},
	{
		"Institucion": "Universidad Tecnológica del Chocó"
	},
	{
		"Institucion": "Universidad Veracruzana"
	},
	{
		"Institucion": "Universidad autónoma de Guadalajara"
	},
	{
		"Institucion": "Universidad autónoma del Estado de Hidalgo"
	},
	{
		"Institucion": "Universidad de Alcalá"
	},
	{
		"Institucion": "Universidad de Antioquia"
	},
	{
		"Institucion": "Universidad de Barcelona"
	},
	{
		"Institucion": "Universidad de Bolonia"
	},
	{
		"Institucion": "Universidad de Bonn"
	},
	{
		"Institucion": "Universidad de Burgos"
	},
	{
		"Institucion": "Universidad de Colima"
	},
	{
		"Institucion": "Universidad de Colorado"
	},
	{
		"Institucion": "Universidad de Córdoba"
	},
	{
		"Institucion": "Universidad de Granada"
	},
	{
		"Institucion": "Universidad de Guadalajara"
	},
	{
		"Institucion": "Universidad de Guanajuato"
	},
	{
		"Institucion": "Universidad de Guelph"
	},
	{
		"Institucion": "Universidad de Illinois"
	},
	{
		"Institucion": "Universidad de Loyola"
	},
	{
		"Institucion": "Universidad de Monterrey"
	},
	{
		"Institucion": "Universidad de Málaga"
	},
	{
		"Institucion": "Universidad de Nayarit"
	},
	{
		"Institucion": "Universidad de New Brunswick"
	},
	{
		"Institucion": "Universidad de Nuevo México"
	},
	{
		"Institucion": "Universidad de Oslo"
	},
	{
		"Institucion": "Universidad de Palermo"
	},
	{
		"Institucion": "Universidad de París"
	},
	{
		"Institucion": "Universidad de París Cité"
	},
	{
		"Institucion": "Universidad de París Sud"
	},
	{
		"Institucion": "Universidad de Quintana Roo"
	},
	{
		"Institucion": "Universidad de Sevilla"
	},
	{
		"Institucion": "Universidad de Sonora"
	},
	{
		"Institucion": "Universidad de Sorbonne"
	},
	{
		"Institucion": "Universidad de Stuttgart"
	},
	{
		"Institucion": "Universidad de Valladolid"
	},
	{
		"Institucion": "Universidad de Wesleyan"
	},
	{
		"Institucion": "Universidad de la Plata"
	},
	{
		"Institucion": "Universidad de las Americas"
	},
	{
		"Institucion": "Universidad del Ceribe"
	},
	{
		"Institucion": "Universidad del Golfo"
	},
	{
		"Institucion": "Universidad del Mar"
	},
	{
		"Institucion": "Universidad del Sur de  California "
	},
	{
		"Institucion": "Universidad del Sur de Ontario"
	},
	{
		"Institucion": "Universidad del Valle de México"
	},
	{
		"Institucion": "Universidade Estatal Paulista"
	},
	{
		"Institucion": "Universitat de Barcelona"
	},
	{
		"Institucion": "University of Calgary"
	},
	{
		"Institucion": "University of California"
	},
	{
		"Institucion": "University of Cambrige"
	},
	{
		"Institucion": "University of Colorado Boulder"
	},
	{
		"Institucion": "University of Michigan"
	},
	{
		"Institucion": "University of Minnesota"
	},
	{
		"Institucion": "University of North Texas"
	},
	{
		"Institucion": "University of Nottingham"
	},
	{
		"Institucion": "University of Southern Indiana"
	},
	{
		"Institucion": "University of Tasmania"
	},
	{
		"Institucion": "University of Texas"
	},
	{
		"Institucion": "University of Texas at Arlington"
	},
	{
		"Institucion": "University of Texas at Austin"
	},
	{
		"Institucion": "University of Washington"
	},
	{
		"Institucion": "University of Wisconsin"
	},
	{
		"Institucion": "Universitá degli studi di Milano"
	},
	{
		"Institucion": "Université Joseph Fourier"
	},
	{
		"Institucion": "Valparaiso University"
	},
	{
		"Institucion": "Virginiu Polytechnic Institute und State University"
	},
	{
		"Institucion": "Washington State University"
	},
	{
		"Institucion": "Yale"
	}
]